wormimtools/Processing.py
wormimtools/Reg_NeuralNet.py
wormimtools/__init__.py
wormimtools/con_auto_dir.py
wormimtools/utils/__init__.py
wormimtools/utils/rme_parser.py
wormimtools/utils/utils.py
wormimtools-1.0.0.dist-info/LICENSE
wormimtools-1.0.0.dist-info/METADATA
wormimtools-1.0.0.dist-info/WHEEL
wormimtools-1.0.0.dist-info/top_level.txt
wormimtools-1.0.0.dist-info/RECORD
