Metadata-Version: 2.1
Name: wormimtools
Version: 1.0.0
Summary: A short description of my package
Home-page: https://github.com/moore-andrew05/imtools
Author: Andrew Moore
Author-email: moore.andrew0598@gmail.com
Classifier: Programming Language :: Python :: 3
Classifier: License :: OSI Approved :: MIT License
Classifier: Operating System :: OS Independent
Requires-Python: >=3.6
License-File: LICENSE
Requires-Dist: numpy
Requires-Dist: scipy
Requires-Dist: matplotlib
Requires-Dist: pandas
Requires-Dist: scikit-image
